spam/__init__.py
spam/command.py
spam/tally.py
spamfinder-0.1.1.dist-info/DESCRIPTION.rst
spamfinder-0.1.1.dist-info/METADATA
spamfinder-0.1.1.dist-info/RECORD
spamfinder-0.1.1.dist-info/WHEEL
spamfinder-0.1.1.dist-info/entry_points.txt
spamfinder-0.1.1.dist-info/metadata.json
spamfinder-0.1.1.dist-info/top_level.txt
