Metadata-Version: 2.0
Name: spamfinder
Version: 0.1.1
Summary: Find the most common senders in your inbox
Home-page: https://github.com/orf/spam/
Author: orf
Author-email: tom@tomforb.es
License: UNKNOWN
Platform: UNKNOWN
Requires-Dist: ascii-graph
Requires-Dist: docopt
Requires-Dist: tqdm
